{
  "configVersion": 1,
  "index": "/index.html",
  "assetGroups": [
    {
      "name": "app",
      "installMode": "prefetch",
      "updateMode": "prefetch",
      "urls": [
        "/favicon.ico",
        "/index.html",
        "/inline.318b50c57b4eba3d437b.bundle.js",
        "/main.18afe165630dafc008e6.bundle.js",
        "/polyfills.bf95165a1d5098766b92.bundle.js",
        "/styles.ac89bfdd6de82636b768.bundle.css"
      ],
      "patterns": []
    },
    {
      "name": "assets",
      "installMode": "lazy",
      "updateMode": "prefetch",
      "urls": [
        "/assets/icons/icon-128x128.png",
        "/assets/icons/icon-144x144.png",
        "/assets/icons/icon-152x152.png",
        "/assets/icons/icon-192x192.png",
        "/assets/icons/icon-384x384.png",
        "/assets/icons/icon-512x512.png",
        "/assets/icons/icon-72x72.png",
        "/assets/icons/icon-96x96.png"
      ],
      "patterns": [
        "https:\\/\\/fonts\\.googleapis\\.com\\/.*"
      ]
    }
  ],
  "dataGroups": [],
  "hashTable": {
    "/inline.318b50c57b4eba3d437b.bundle.js": "998c6060446975e566fd17509558ddc68d72eec3",
    "/assets/icons/icon-128x128.png": "31042aca75327ca858edcbf6ca0ebccbc6b72cd4",
    "/main.18afe165630dafc008e6.bundle.js": "319a71a4b2fb74fd89cb9d30ddecd5e7d3fdd886",
    "/assets/icons/icon-144x144.png": "b76f326f9da54f802eab34018fdebe18a73066e2",
    "/polyfills.bf95165a1d5098766b92.bundle.js": "5f49131c0c147a20f91b1e77814434e0c77bd3dc",
    "/assets/icons/icon-152x152.png": "c67ad631ffa3c2cd016a3c299f933727c5f74318",
    "/styles.ac89bfdd6de82636b768.bundle.css": "da39a3ee5e6b4b0d3255bfef95601890afd80709",
    "/assets/icons/icon-192x192.png": "266d1467c7c22ef83eeccce17a41f0a711a89442",
    "/favicon.ico": "57b5b1841d2475f4922d18e040ce9bdce37bd9c0",
    "/assets/icons/icon-384x384.png": "6eb57de9a119409011500f0b5d083dfa2d3fb19a",
    "/index.html": "84e575b13987b5e0b538e6d068e630fbd98df824",
    "/assets/icons/icon-512x512.png": "fd7b58d0bdb021ca9d1eeff8896ce7fd1bf746b4",
    "/assets/icons/icon-72x72.png": "d407dedcbeee542381dcc60dcaffa9d2ba06639b",
    "/assets/icons/icon-96x96.png": "b4164ddba06e050ffbb286f06bea30b5c75771d5"
  }
}